Metadata-Version: 2.1
Name: lktest-netbox-plugin-account-management
Version: 1.0.0
Summary: ADESTIS Account Management
Home-page: https://github.com/adestis/netbox-account-management
Author: ADESTIS GmbH
Author-email: pypi@adestis.de
Maintainer: ADESTIS GmbH
Maintainer-email: pypi@adestis.de
License: GPLv3
Project-URL: Source, https://github.com/adestis/netbox-account-management
Keywords: netbox,netbox-plugin,plugin
Classifier: License :: OSI Approved :: GNU General Public License v3 (GPLv3)
Classifier: Framework :: Django
Classifier: Programming Language :: Python :: 3
License-File: LICENSE
Requires-Dist: paramiko
